dom_inspector_ai/__init__.py
dom_inspector_ai/analyzer.py
dom_inspector_ai/extractor.py
dom_inspector_ai/screenshot.py
dom_inspector_ai-0.1.1.dist-info/licenses/LICENSE
dom_inspector_ai-0.1.1.dist-info/METADATA
dom_inspector_ai-0.1.1.dist-info/WHEEL
dom_inspector_ai-0.1.1.dist-info/top_level.txt
dom_inspector_ai-0.1.1.dist-info/RECORD
