Metadata-Version: 2.4
Name: dom-inspector-ai
Version: 0.1.1
Summary: Extract class/id and DOM paths with screenshot for AI agents
Author-email: Your Name <yutotkg.1040@gmail.com>
Requires-Python: >=3.8
License-File: LICENSE
Requires-Dist: beautifulsoup4
Requires-Dist: selenium
Requires-Dist: requests
Dynamic: license-file
